[
    {
        "pk": 1,
        "model": "scheduler.academicinstitution",
        "fields": {
            "established_on": "1974-08-24",
            "name": "Concordia University"
        }
    },
    {
        "pk": 2,
        "model": "scheduler.faculty",
        "fields": {
            "university": 1,
            "name": "Engineering and Computer Science",
            "description": "Engineering and Computer Science ENCS"
        }
    },
    {
        "pk": 1,
        "model": "scheduler.academicprogram",
        "fields": {
            "required_gpa": "2.8",
            "total_required_credits": 60,
            "type": "U",
            "name": "Bachelor of Software Engineering",
            "faculty": 2
        }
    },
    {
        "pk": 2,
        "model": "scheduler.academicprogram",
        "fields": {
            "required_gpa": "2.8",
            "total_required_credits": 40,
            "type": "G",
            "name": "Masters of Software Engineering",
            "faculty": 2
        }
    },
    {
        "pk": 3,
        "model": "scheduler.academicprogram",
        "fields": {
            "required_gpa": "2.8",
            "total_required_credits": 60,
            "type": "U",
            "name": "Bachelors of Computer Science",
            "faculty": 2
        }
    },
    {
        "pk": 4,
        "model": "scheduler.academicprogram",
        "fields": {
            "required_gpa": "2.8",
            "total_required_credits": 40,
            "type": "G",
            "name": "Masters of Computer Science",
            "faculty": 2
        }
    },
    {
        "pk": 1,
        "model": "scheduler.course",
        "fields": {
            "faculty": 2,
            "name": "ELEC 275",
            "course_credits": 4,
            "description": "Principles of Electrical Engineering"
        }
    },
    {
        "pk": 2,
        "model": "scheduler.course",
        "fields": {
            "faculty": 2,
            "name": "ENCS 282",
            "course_credits": 4,
            "description": "Technical Writing and Communication"
        }
    },
    {
        "pk": 3,
        "model": "scheduler.course",
        "fields": {
            "faculty": 2,
            "name": "ENGR 201",
            "course_credits": 4,
            "description": "Professional Practice and Responsibility"
        }
    },
    {
        "pk": 4,
        "model": "scheduler.course",
        "fields": {
            "faculty": 2,
            "name": "ENGR 202",
            "course_credits": 4,
            "description": "Sustainable Development and Environmental Stewardship"
        }
    },
    {
        "pk": 5,
        "model": "scheduler.course",
        "fields": {
            "faculty": 2,
            "name": "ENGR 213",
            "course_credits": 4,
            "description": "Applied Ordinary Differential Equations"
        }
    },
    {
        "pk": 6,
        "model": "scheduler.course",
        "fields": {
            "faculty": 2,
            "name": "ENGR 233",
            "course_credits": 4,
            "description": "Applied Advanced Calculus"
        }
    },
    {
        "pk": 7,
        "model": "scheduler.course",
        "fields": {
            "faculty": 2,
            "name": "ENGR 301",
            "course_credits": 4,
            "description": "Engineering Management Principles and Economics"
        }
    },
    {
        "pk": 8,
        "model": "scheduler.course",
        "fields": {
            "faculty": 2,
            "name": "ENGR 371",
            "course_credits": 4,
            "description": "Probability and Statistics in Engineering"
        }
    },
    {
        "pk": 9,
        "model": "scheduler.course",
        "fields": {
            "faculty": 2,
            "name": "ENGR 391",
            "course_credits": 4,
            "description": "Numerical Methods in Engineering"
        }
    },
    {
        "pk": 10,
        "model": "scheduler.course",
        "fields": {
            "faculty": 2,
            "name": "ENGR 392",
            "course_credits": 4,
            "description": "Impact of Technology on Society"
        }
    },
    {
        "pk": 11,
        "model": "scheduler.course",
        "fields": {
            "faculty": 2,
            "name": "SOEN 228",
            "course_credits": 4,
            "description": "System Hardware"
        }
    },
    {
        "pk": 12,
        "model": "scheduler.course",
        "fields": {
            "faculty": 2,
            "name": "SOEN 287",
            "course_credits": 4,
            "description": "Web Programming"
        }
    },
    {
        "pk": 13,
        "model": "scheduler.course",
        "fields": {
            "faculty": 2,
            "name": "SOEN 331",
            "course_credits": 4,
            "description": "Introduction to Formal Methods for Software Engineering"
        }
    },
    {
        "pk": 14,
        "model": "scheduler.course",
        "fields": {
            "faculty": 2,
            "name": "SOEN 341",
            "course_credits": 4,
            "description": "Software Process"
        }
    },
    {
        "pk": 15,
        "model": "scheduler.course",
        "fields": {
            "faculty": 2,
            "name": "SOEN 342",
            "course_credits": 4,
            "description": "Software Requirements and Specifications"
        }
    },
    {
        "pk": 16,
        "model": "scheduler.course",
        "fields": {
            "faculty": 2,
            "name": "SOEN 343",
            "course_credits": 4,
            "description": "Software Architecture and Design I "
        }
    },
    {
        "pk": 17,
        "model": "scheduler.course",
        "fields": {
            "faculty": 2,
            "name": "SOEN 344",
            "course_credits": 4,
            "description": "Software Architecture and Design II"
        }
    },
    {
        "pk": 18,
        "model": "scheduler.course",
        "fields": {
            "faculty": 2,
            "name": "SOEN 345",
            "course_credits": 4,
            "description": "Software Testing, Verification and Quality Assurance"
        }
    },
    {
        "pk": 19,
        "model": "scheduler.course",
        "fields": {
            "faculty": 2,
            "name": "SOEN 357",
            "course_credits": 4,
            "description": "User Interface Design "
        }
    },
    {
        "pk": 20,
        "model": "scheduler.course",
        "fields": {
            "faculty": 2,
            "name": "SOEN 384",
            "course_credits": 4,
            "description": "Management, Measurement and Quality Control"
        }
    },
    {
        "pk": 21,
        "model": "scheduler.course",
        "fields": {
            "faculty": 2,
            "name": "SOEN 385",
            "course_credits": 4,
            "description": "Control Systems and Applications "
        }
    },
    {
        "pk": 22,
        "model": "scheduler.course",
        "fields": {
            "faculty": 2,
            "name": "SOEN 390",
            "course_credits": 4,
            "description": "Software Engineering Team Design Project"
        }
    },
    {
        "pk": 23,
        "model": "scheduler.course",
        "fields": {
            "faculty": 2,
            "name": "SOEN 490",
            "course_credits": 4,
            "description": "Capstone Software Engineering Design Project"
        }
    },
    {
        "pk": 1,
        "model": "scheduler.academicrequirement",
        "fields": {
            "academic_program": 1,
            "required_credits": 30,
            "name": "Engineering Core",
            "allowable_courses": [1, 2, 3, 4, 5, 6, 7, 8, 9, 10]
        }
    },
    {
        "pk": 2,
        "model": "scheduler.academicrequirement",
        "fields": {
            "academic_program": 1,
            "required_credits": 66,
            "name": "Software Engineering Core",
            "allowable_courses": [11, 12, 13, 14, 15, 16, 17, 18, 19, 20, 21, 22, 23]
        }
    },
    {
        "pk": 1,
        "model": "scheduler.building",
        "fields": {
            "province": "QC",
            "city": "Montreal",
            "name": "Hall Building",
            "country": "CANADA",
            "postal_code": "H3C5M1",
            "address": "1455 De Maisonneuve W."
        }
    }
]